opencode/__init__.py
opencode/events.py
opencode/agent/__init__.py
opencode/agent/base.py
opencode/agent/build.py
opencode/agent/explore.py
opencode/agent/plan.py
opencode/agent/registry.py
opencode/cli/__init__.py
opencode/cli/main.py
opencode/commands/__init__.py
opencode/commands/builtins.py
opencode/commands/registry.py
opencode/config/__init__.py
opencode/config/keybind.py
opencode/config/paths.py
opencode/config/settings.py
opencode/config/storage.py
opencode/config/theme.py
opencode/provider/__init__.py
opencode/provider/anthropic.py
opencode/provider/base.py
opencode/provider/openai.py
opencode/provider/registry.py
opencode/rlm/__init__.py
opencode/rlm/archive.py
opencode/rlm/context.py
opencode/rlm/handler.py
opencode/rlm/retrieve.py
opencode/rlm/search.py
opencode/session/__init__.py
opencode/session/export.py
opencode/session/manager.py
opencode/session/share.py
opencode/tool/__init__.py
opencode/tool/base.py
opencode/tool/bash.py
opencode/tool/edit.py
opencode/tool/glob.py
opencode/tool/grep.py
opencode/tool/memory.py
opencode/tool/question.py
opencode/tool/read.py
opencode/tool/registry.py
opencode/tool/task.py
opencode/tool/todo.py
opencode/tool/webfetch.py
opencode/tool/write.py
opencode/tui/__init__.py
opencode/tui/app.py
opencode/tui/dialogs/__init__.py
opencode/tui/dialogs/agent.py
opencode/tui/dialogs/command.py
opencode/tui/dialogs/model.py
opencode/tui/dialogs/session.py
opencode/tui/dialogs/theme.py
opencode/tui/widgets/__init__.py
opencode/tui/widgets/context_bar.py
opencode/tui/widgets/footer.py
opencode/tui/widgets/header.py
opencode/tui/widgets/message.py
opencode/tui/widgets/prompt.py
opencode/tui/widgets/sidebar.py
opencode_rlm-0.1.0.dist-info/METADATA
opencode_rlm-0.1.0.dist-info/WHEEL
opencode_rlm-0.1.0.dist-info/entry_points.txt
opencode_rlm-0.1.0.dist-info/licenses/LICENSE
opencode_rlm-0.1.0.dist-info/RECORD
